{
    "name": "common",
    "source": null,
    "target": null,
    "config_env_matches": {
        "MYSQL_PASSWORD": "COMMON_MYSQL_PASSWORD"
    },
    "server_engine": {
        "name": "Airplane",
        "version": "1.17.1",
        "target": "server.jar"
    },
    "plugins": {
        "BookExploitFix": "1.2",
        "BungeeTabListPlusBridge": "3.6.*",
        "FastAsyncWorldEdit": "1.17-*",
        "LuckPerms": "5.4.*",
        "RedCraftReboot": "0.0.*",
        "RedstoneClockDetector": "1.2.1",
        "SelectionVisualizer": "3.2.0.*",
        "goBrush": "3.8.*",
        "goPaint": "3.1.*",
        "spark": "1.8.*"
    }
}